wot_datfile_parser_py-0.2.1.dist-info/METADATA
wot_datfile_parser_py-0.2.1.dist-info/WHEEL
wot_datfile_parser_py/__init__.py
wot_datfile_parser_py/wot_datfile_parser_py.cpython-310-x86_64-linux-gnu.so
wot_datfile_parser_py-0.2.1.dist-info/RECORD
